Metadata-Version: 2.1
Name: my-scp
Version: 2018.5.15
Summary: Remote copy and download files or directories via SCP.
Home-page: https://github.com/xiuyuanjun/my_scp.git
Author: xiuyuanjun
Author-email: 729125866@qq.com
License: GNU
Project-URL: Bug Reports, https://github.com/xiuyuanjun/my_scp/issues
Project-URL: Source, https://github.com/xiuyuanjun/my_scp/
Keywords: Remote copy and download files or directories via SCP.
Platform: UNKNOWN
Classifier: Programming Language :: Python :: 2
Classifier: Programming Language :: Python :: 2.7
Classifier: Programming Language :: Python :: 3
Classifier: Programming Language :: Python :: 3.4
Classifier: Programming Language :: Python :: 3.5
Classifier: Programming Language :: Python :: 3.6
Provides-Extra: test
Provides-Extra: dev
